{
  "keyword": "田中将大",
  "name": "広島東洋カープ スマホケース 手帳型 背番 マグネットなし あり 選べる xpe",
  "price": 3650,
  "url": "https://hb.afl.rakuten.co.jp/hgc/g00rfgan.33htzfa7.g00rfgan.33hu0dd4/?pc=https%3A%2F%2Fitem.rakuten.co.jp%2Fkougalog%2Fdy-carp-uni02%2F&m=http%3A%2F%2Fm.rakuten.co.jp%2Fkougalog%2Fi%2F11068589%2F&rafcid=wsc_i_is_5fc8e544-5fe0-4551-9782-4f7da9587a4f",
  "image_url": "https://thumbnail.image.rakuten.co.jp/@0_mall/kougalog/cabinet/design/diary5/dy-carp-uni02.jpg?_ex=128x128",
  "updated_at": "2026-07-08T08:05:09.703587+09:00"
}